Metadata-Version: 2.1
Name: gcrypter
Version: 0.3
Summary: Encryption algorithm based on bytes and their correspondent numbers to encode strings
Home-page: https://github.com/Nurul-GC/gcrypter
Author: Nurul-GC
Author-email: nuruldecarvalhol@gmail.com
License: BSD 3-Clause
Download-URL: https://github.com/Nurul-GC/gcrypter/archive/refs/tags/
Project-URL: Bug Tracker, https://github.com/Nurul-GC/gcrypter/issues
Keywords: python-encryption,encryption-decryption,encryption-algorithm
Platform: UNKNOWN
Classifier: Development Status :: 5 - Production/Stable
Classifier: Intended Audience :: Developers
Classifier: Topic :: Software Development :: Build Tools
Classifier: Programming Language :: Python :: 3
Classifier: Programming Language :: Python :: 3.6
Classifier: Programming Language :: Python :: 3.7
Classifier: Programming Language :: Python :: 3.8
Classifier: Programming Language :: Python :: 3.9
Requires-Python: >=3.6
License-File: LICENSE
